{
  "problem_name": "count-the-hidden-sequences",
  "data_structures": [
    [
      "integer"
    ]
  ],
  "category": "Math & Geometry",
  "algorithm_technique": [
    "Calculate prefix sums of differences to find the range of possible values for the first element."
  ],
  "problem_summary_simple": "Find how many sequences fit given differences and a value range.",
  "problem_summary_technical": "Determine the minimum and maximum possible values of the hidden sequence elements based on differences and the range [lower, upper].",
  "time_complexity": [
    "O(n)"
  ],
  "space_complexity": [
    "O(1)"
  ],
  "key_insights": [
    [
      "The problem can be reframed as finding the possible starting values for the hidden sequence.",
      "The differences define relative changes, and the range [lower, upper] constrains absolute values.",
      "The number of valid starting values is determined by the available 'slack' between the required range and the given [lower, upper] bounds."
    ]
  ],
  "difficulty_level": "Medium",
  "analysis_timestamp": "2025-07-16 21:38:05",
  "batch_processed": true,
  "batch_size": 5
}